{"path":"%D0%9A%D0%BE%D1%87%D0%B5%D0%B4%D1%8B%D0%B6%D0%BD%D0%B8%D0%BA%20%D0%B6%D0%B5%D0%BD%D1%81%D0%BA%D0%B8%D0%B9%20%28Athyrium%20filix-femina%29","deepCounters":{"total":3,"images":3,"files":3},"counters":{"total":3,"images":3,"files":3},"thumb":{"path":"thumbs\/DSC03283.jpg","width":640,"height":480},"thumbCaption":"<h3>Кочедыжник женский (Athyrium filix-femina)<\/h3>","album":{"description":"Plantarium.INFO. Plant anatomy, Hybrids, Pests and Diseases, Carnivorous, Myco-Heterotrophic, Parasitic, Albinos, Fungi, Succulents, Cactuses, Aquatic, Nut-fruited, Tuberous, Ferns, Mosses, Bulbs, Mutants, Witches' brooms, Fairy rings, Prolific petals, Bad luck, Good luck, Colors, Burls, Mycelium, Molds, Journeys.\n<br\/><br\/>\nVisit also Main site of plants and herbs: <a href=\"http:\/\/herbarium.info\">Herbarium.INFO<\/a><br\/>","title":"Plantarium.INFO Herbs Appendix"},"objects":[{"image":{"path":"slides\/DSC03283.jpg","width":768,"height":1024},"thumb":{"path":"thumbs\/DSC03283.jpg","width":640,"height":480},"thumbCaption":"<span class=\"nr\">1<\/span>  <small>                               <\/small>","photodata":"<p><b>Original Date<\/b> <i>6\/22\/10 12:52 PM<\/i><\/p><p><b>Camera<\/b> <i>DSC-T30<\/i><\/p><p><b>Focal Length (35mm)<\/b> <i>38mm<\/i><\/p><p><b>Metering Mode<\/b> <i>Multi-segment<\/i><\/p><p><b>ISO Equivalent<\/b> <i>125<\/i><\/p><p><b>Exposure Time<\/b> <i>1\/250s<\/i><\/p><p><b>Aperture<\/b> <i>5.599999904632568<\/i><\/p><p><b>Exposure bias<\/b> <i>0 EV<\/i><\/p><p><b>Exposure Program<\/b> <i>Program normal<\/i><\/p><p><b>White balance<\/b> <i>Auto white balance<\/i><\/p><p><b>Flash<\/b> <i>Flash did not fire, auto<\/i><\/p><p><b>Resolution<\/b> <i>1536 x 2048<\/i><\/p>","fileDate":"2010-06-24T16:53:44.0Z","modifiedDays":14782.0,"path":"DSC03283.jpg","imageCaption":"<h5>DSC03283<\/h5><div class=\"comment\">                               <\/div>","fileSize":1279969,"epochDate":1.277196746E12,"name":"DSC03283.jpg","comment":"                               ","category":"image","camera":{"aperture":5.6,"exposureTime":"1\/250s","originalDate":"2010-06-22T12:52:26.0Z","cameraModel":"DSC-T30","focalLength35mm":"38mm","resolution":"1536 x 2048","cameraMake":"SONY","isoEquivalent":125,"flash":"Flash did not fire, auto","focalLength":"6mm"}},{"image":{"path":"slides\/DSC03296.jpg","width":1024,"height":768},"thumb":{"path":"thumbs\/DSC03296.jpg","width":640,"height":480},"thumbCaption":"<span class=\"nr\">2<\/span>  <small>                               <\/small>","photodata":"<p><b>Original Date<\/b> <i>6\/22\/10 1:06 PM<\/i><\/p><p><b>Camera<\/b> <i>DSC-T30<\/i><\/p><p><b>Focal Length (35mm)<\/b> <i>38mm<\/i><\/p><p><b>Metering Mode<\/b> <i>Multi-segment<\/i><\/p><p><b>ISO Equivalent<\/b> <i>125<\/i><\/p><p><b>Exposure Time<\/b> <i>1\/200s<\/i><\/p><p><b>Aperture<\/b> <i>5.599999904632568<\/i><\/p><p><b>Exposure bias<\/b> <i>0 EV<\/i><\/p><p><b>Exposure Program<\/b> <i>Program normal<\/i><\/p><p><b>White balance<\/b> <i>Auto white balance<\/i><\/p><p><b>Flash<\/b> <i>Flash did not fire, auto<\/i><\/p><p><b>Resolution<\/b> <i>2048 x 1536<\/i><\/p>","fileDate":"2010-06-22T14:06:58.0Z","modifiedDays":14782.0,"path":"DSC03296.jpg","imageCaption":"<h5>DSC03296<\/h5><div class=\"comment\">                               <\/div>","fileSize":1500238,"epochDate":1.277197619E12,"name":"DSC03296.jpg","comment":"                               ","category":"image","camera":{"aperture":5.6,"exposureTime":"1\/200s","originalDate":"2010-06-22T13:06:59.0Z","cameraModel":"DSC-T30","focalLength35mm":"38mm","resolution":"2048 x 1536","cameraMake":"SONY","isoEquivalent":125,"flash":"Flash did not fire, auto","focalLength":"6mm"}},{"image":{"path":"slides\/DSC03297.jpg","width":768,"height":1024},"thumb":{"path":"thumbs\/DSC03297.jpg","width":640,"height":480},"thumbCaption":"<span class=\"nr\">3<\/span>  <small>                               <\/small>","photodata":"<p><b>Original Date<\/b> <i>6\/22\/10 1:07 PM<\/i><\/p><p><b>Camera<\/b> <i>DSC-T30<\/i><\/p><p><b>Focal Length (35mm)<\/b> <i>38mm<\/i><\/p><p><b>Metering Mode<\/b> <i>Multi-segment<\/i><\/p><p><b>ISO Equivalent<\/b> <i>125<\/i><\/p><p><b>Exposure Time<\/b> <i>1\/200s<\/i><\/p><p><b>Aperture<\/b> <i>5.599999904632568<\/i><\/p><p><b>Exposure bias<\/b> <i>0 EV<\/i><\/p><p><b>Exposure Program<\/b> <i>Program normal<\/i><\/p><p><b>White balance<\/b> <i>Auto white balance<\/i><\/p><p><b>Flash<\/b> <i>Flash did not fire, auto<\/i><\/p><p><b>Resolution<\/b> <i>1536 x 2048<\/i><\/p>","fileDate":"2010-06-24T16:55:06.0Z","modifiedDays":14782.0,"path":"DSC03297.jpg","imageCaption":"<h5>DSC03297<\/h5><div class=\"comment\">                               <\/div>","fileSize":1212635,"epochDate":1.27719763E12,"name":"DSC03297.jpg","comment":"                               ","category":"image","camera":{"aperture":5.6,"exposureTime":"1\/200s","originalDate":"2010-06-22T13:07:10.0Z","cameraModel":"DSC-T30","focalLength35mm":"38mm","resolution":"1536 x 2048","cameraMake":"SONY","isoEquivalent":125,"flash":"Flash did not fire, auto","focalLength":"6mm"}}],"name":"Кочедыжник женский (Athyrium filix-femina)","epochDateRange":"1277196746000,1277197630000","fileDate":"2017-06-17T20:21:00.968Z","modifiedDays":14782.0}