{"path":"%D0%A0%D0%BE%D1%81%D1%81%D0%B8%D0%B3%D0%BB%D0%BE%D1%81%D1%81%D1%83%D0%BC%20%D0%A0%D0%BE%D0%B4%D0%BE%D0%BD%20%D0%94%D0%B6%D0%B5%D1%81%D1%82%D0%B5%D1%80%20%28Rossioglossum%20Rawdon%20Jester%20%28R.%20grande%20x%20R.%20williamsianum%29%29","deepCounters":{"total":2,"images":2,"files":2},"counters":{"total":2,"images":2,"files":2},"thumb":{"path":"thumbs\/DSC05047.JPG","width":640,"height":480},"thumbCaption":"<h3>Россиглоссум Родон Джестер (Rossioglossum Rawdon Jester (R. grande x R. williamsianum))<\/h3>","album":{"description":"Plantarium.INFO. Plant anatomy, Hybrids, Pests and Diseases, Carnivorous, Myco-Heterotrophic, Parasitic, Albinos, Fungi, Succulents, Cactuses, Aquatic, Nut-fruited, Tuberous, Ferns, Mosses, Bulbs, Mutants, Witches' brooms, Fairy rings, Prolific petals, Bad luck, Good luck, Colors, Burls, Mycelium, Molds, Journeys.\n<br\/><br\/>\nVisit also Main site of plants and herbs: <a href=\"http:\/\/herbarium.info\">Herbarium.INFO<\/a><br\/>","title":"Plantarium.INFO Herbs Appendix"},"objects":[{"image":{"path":"slides\/DSC05047.JPG","width":1024,"height":768},"thumb":{"path":"thumbs\/DSC05047.JPG","width":640,"height":480},"thumbCaption":"<span class=\"nr\">1<\/span>  <small>                               <\/small>","photodata":"<p><b>Original Date<\/b> <i>3\/4\/17 2:24 PM<\/i><\/p><p><b>Camera<\/b> <i>DSC-HX90<\/i><\/p><p><b>Focal Length (35mm)<\/b> <i>119mm<\/i><\/p><p><b>Metering Mode<\/b> <i>Multi-segment<\/i><\/p><p><b>ISO Equivalent<\/b> <i>200<\/i><\/p><p><b>Exposure Time<\/b> <i>1\/20s<\/i><\/p><p><b>Aperture<\/b> <i>5.599999904632568<\/i><\/p><p><b>Exposure bias<\/b> <i>0 EV<\/i><\/p><p><b>Exposure Program<\/b> <i>Manual control<\/i><\/p><p><b>White balance<\/b> <i>Manual white balance<\/i><\/p><p><b>Flash<\/b> <i>Flash did not fire, auto<\/i><\/p><p><b>Resolution<\/b> <i>4896 x 3672<\/i><\/p>","fileDate":"2017-03-04T15:24:37.999Z","modifiedDays":17229.0,"path":"DSC05047.JPG","imageCaption":"<h5>DSC05047<\/h5><div class=\"comment\">                               <\/div>","fileSize":6403791,"epochDate":1.488626679E12,"name":"DSC05047.JPG","comment":"                               ","category":"image","camera":{"aperture":5.6,"exposureTime":"1\/20s","originalDate":"2017-03-04T14:24:39.0Z","cameraModel":"DSC-HX90","focalLength35mm":"119mm","resolution":"4896 x 3672","cameraMake":"SONY","isoEquivalent":200,"flash":"Flash did not fire, auto","focalLength":"20mm"}},{"image":{"path":"slides\/DSC05048.JPG","width":1024,"height":768},"thumb":{"path":"thumbs\/DSC05048.JPG","width":640,"height":480},"thumbCaption":"<span class=\"nr\">2<\/span>  <small>                               <\/small>","photodata":"<p><b>Original Date<\/b> <i>3\/4\/17 2:24 PM<\/i><\/p><p><b>Camera<\/b> <i>DSC-HX90<\/i><\/p><p><b>Focal Length (35mm)<\/b> <i>154mm<\/i><\/p><p><b>Metering Mode<\/b> <i>Multi-segment<\/i><\/p><p><b>ISO Equivalent<\/b> <i>200<\/i><\/p><p><b>Exposure Time<\/b> <i>1\/20s<\/i><\/p><p><b>Aperture<\/b> <i>5.599999904632568<\/i><\/p><p><b>Exposure bias<\/b> <i>0 EV<\/i><\/p><p><b>Exposure Program<\/b> <i>Manual control<\/i><\/p><p><b>White balance<\/b> <i>Manual white balance<\/i><\/p><p><b>Flash<\/b> <i>Flash did not fire, auto<\/i><\/p><p><b>Resolution<\/b> <i>4896 x 3672<\/i><\/p>","fileDate":"2017-03-04T15:24:51.999Z","modifiedDays":17229.0,"path":"DSC05048.JPG","imageCaption":"<h5>DSC05048<\/h5><div class=\"comment\">                               <\/div>","fileSize":6279048,"epochDate":1.48862669E12,"name":"DSC05048.JPG","comment":"                               ","category":"image","camera":{"aperture":5.6,"exposureTime":"1\/20s","originalDate":"2017-03-04T14:24:50.0Z","cameraModel":"DSC-HX90","focalLength35mm":"154mm","resolution":"4896 x 3672","cameraMake":"SONY","isoEquivalent":200,"flash":"Flash did not fire, auto","focalLength":"26mm"}}],"name":"Россиглоссум Родон Джестер (Rossioglossum Rawdon Jester (R. grande x R. williamsianum))","epochDateRange":"1488626679000,1488626690000","fileDate":"2017-06-18T15:39:05.877Z","modifiedDays":17229.0}