{"path":"%D0%A7%D0%BE%D0%B7%D0%B5%D0%BD%D0%B8%D1%8F%20%D1%82%D0%BE%D0%BB%D0%BE%D0%BA%D0%BD%D1%8F%D0%BD%D0%BA%D0%BE%D0%BB%D0%B8%D1%81%D1%82%D0%BD%D0%B0%D1%8F%20%28Chosenia%20arbutifolia%29","deepCounters":{"total":5,"images":5,"files":5},"counters":{"total":5,"images":5,"files":5},"thumb":{"path":"thumbs\/DSC02046.jpg","width":640,"height":480},"thumbCaption":"<h3>Чозения толокнянколистная (Chosenia arbutifolia)<\/h3>","album":{"description":"Plantarium.INFO. Plant anatomy, Hybrids, Pests and Diseases, Carnivorous, Myco-Heterotrophic, Parasitic, Albinos, Fungi, Succulents, Cactuses, Aquatic, Nut-fruited, Tuberous, Ferns, Mosses, Bulbs, Mutants, Witches' brooms, Fairy rings, Prolific petals, Bad luck, Good luck, Colors, Burls, Mycelium, Molds, Journeys.\n<br\/><br\/>\nVisit also Main site of plants and herbs: <a href=\"http:\/\/herbarium.info\">Herbarium.INFO<\/a><br\/>","title":"Plantarium.INFO Herbs Appendix"},"objects":[{"image":{"path":"slides\/DSC02041.jpg","width":768,"height":1024},"thumb":{"path":"thumbs\/DSC02041.jpg","width":640,"height":480},"thumbCaption":"<span class=\"nr\">1<\/span>  <small>                               <\/small>","photodata":"<p><b>Original Date<\/b> <i>4\/25\/15 12:48 PM<\/i><\/p><p><b>Camera<\/b> <i>DSC-HX50<\/i><\/p><p><b>Focal Length<\/b> <i>4.3 mm<\/i><\/p><p><b>Metering Mode<\/b> <i>Multi-segment<\/i><\/p><p><b>ISO Equivalent<\/b> <i>80<\/i><\/p><p><b>Exposure Time<\/b> <i>1\/80s<\/i><\/p><p><b>Aperture<\/b> <i>3.5<\/i><\/p><p><b>Exposure bias<\/b> <i>0 EV<\/i><\/p><p><b>Exposure Program<\/b> <i>Program normal<\/i><\/p><p><b>White balance<\/b> <i>Auto white balance<\/i><\/p><p><b>Flash<\/b> <i>Flash did not fire, auto<\/i><\/p><p><b>Resolution<\/b> <i>5184 x 3888<\/i><\/p>","fileDate":"2015-04-25T16:39:59.0Z","modifiedDays":16550.0,"path":"DSC02041.jpg","imageCaption":"<h5>DSC02041<\/h5><div class=\"comment\">                               <\/div>","fileSize":7149475,"epochDate":1.429955333E12,"name":"DSC02041.jpg","comment":"                               ","category":"image","camera":{"aperture":3.5,"exposureTime":"1\/80s","originalDate":"2015-04-25T12:48:53.0Z","cameraModel":"DSC-HX50","resolution":"5184 x 3888","cameraMake":"SONY","isoEquivalent":80,"flash":"Flash did not fire, auto","focalLength":"4mm"}},{"image":{"path":"slides\/DSC02043.jpg","width":1024,"height":768},"thumb":{"path":"thumbs\/DSC02043.jpg","width":640,"height":480},"thumbCaption":"<span class=\"nr\">2<\/span>  <small>                               <\/small>","photodata":"<p><b>Original Date<\/b> <i>4\/25\/15 12:49 PM<\/i><\/p><p><b>Camera<\/b> <i>DSC-HX50<\/i><\/p><p><b>Focal Length<\/b> <i>4.3 mm<\/i><\/p><p><b>Metering Mode<\/b> <i>Multi-segment<\/i><\/p><p><b>ISO Equivalent<\/b> <i>80<\/i><\/p><p><b>Exposure Time<\/b> <i>1\/800s<\/i><\/p><p><b>Aperture<\/b> <i>3.5<\/i><\/p><p><b>Exposure bias<\/b> <i>0 EV<\/i><\/p><p><b>Exposure Program<\/b> <i>Program normal<\/i><\/p><p><b>White balance<\/b> <i>Auto white balance<\/i><\/p><p><b>Flash<\/b> <i>Flash did not fire, auto<\/i><\/p><p><b>Resolution<\/b> <i>5184 x 3888<\/i><\/p>","fileDate":"2015-04-25T16:40:00.0Z","modifiedDays":16550.0,"path":"DSC02043.jpg","imageCaption":"<h5>DSC02043<\/h5><div class=\"comment\">                               <\/div>","fileSize":5042336,"epochDate":1.429955356E12,"name":"DSC02043.jpg","comment":"                               ","category":"image","camera":{"aperture":3.5,"exposureTime":"1\/800s","originalDate":"2015-04-25T12:49:16.0Z","cameraModel":"DSC-HX50","resolution":"5184 x 3888","cameraMake":"SONY","isoEquivalent":80,"flash":"Flash did not fire, auto","focalLength":"4mm"}},{"image":{"path":"slides\/DSC02044.jpg","width":1024,"height":768},"thumb":{"path":"thumbs\/DSC02044.jpg","width":640,"height":480},"thumbCaption":"<span class=\"nr\">3<\/span>  <small>                               <\/small>","photodata":"<p><b>Original Date<\/b> <i>4\/25\/15 12:49 PM<\/i><\/p><p><b>Camera<\/b> <i>DSC-HX50<\/i><\/p><p><b>Focal Length<\/b> <i>4.3 mm<\/i><\/p><p><b>Metering Mode<\/b> <i>Multi-segment<\/i><\/p><p><b>ISO Equivalent<\/b> <i>80<\/i><\/p><p><b>Exposure Time<\/b> <i>1\/800s<\/i><\/p><p><b>Aperture<\/b> <i>3.5<\/i><\/p><p><b>Exposure bias<\/b> <i>0 EV<\/i><\/p><p><b>Exposure Program<\/b> <i>Program normal<\/i><\/p><p><b>White balance<\/b> <i>Auto white balance<\/i><\/p><p><b>Flash<\/b> <i>Flash did not fire, auto<\/i><\/p><p><b>Resolution<\/b> <i>5184 x 3888<\/i><\/p>","fileDate":"2015-04-25T16:40:01.0Z","modifiedDays":16550.0,"path":"DSC02044.jpg","imageCaption":"<h5>DSC02044<\/h5><div class=\"comment\">                               <\/div>","fileSize":5155503,"epochDate":1.42995536E12,"name":"DSC02044.jpg","comment":"                               ","category":"image","camera":{"aperture":3.5,"exposureTime":"1\/800s","originalDate":"2015-04-25T12:49:20.0Z","cameraModel":"DSC-HX50","resolution":"5184 x 3888","cameraMake":"SONY","isoEquivalent":80,"flash":"Flash did not fire, auto","focalLength":"4mm"}},{"image":{"path":"slides\/DSC02045.jpg","width":1024,"height":768},"thumb":{"path":"thumbs\/DSC02045.jpg","width":640,"height":480},"thumbCaption":"<span class=\"nr\">4<\/span>  <small>                               <\/small>","photodata":"<p><b>Original Date<\/b> <i>4\/25\/15 12:49 PM<\/i><\/p><p><b>Camera<\/b> <i>DSC-HX50<\/i><\/p><p><b>Focal Length<\/b> <i>4.3 mm<\/i><\/p><p><b>Metering Mode<\/b> <i>Multi-segment<\/i><\/p><p><b>ISO Equivalent<\/b> <i>80<\/i><\/p><p><b>Exposure Time<\/b> <i>1\/640s<\/i><\/p><p><b>Aperture<\/b> <i>3.5<\/i><\/p><p><b>Exposure bias<\/b> <i>0 EV<\/i><\/p><p><b>Exposure Program<\/b> <i>Landscape mode<\/i><\/p><p><b>White balance<\/b> <i>Auto white balance<\/i><\/p><p><b>Flash<\/b> <i>Flash did not fire, auto<\/i><\/p><p><b>Resolution<\/b> <i>5184 x 3888<\/i><\/p>","fileDate":"2015-04-25T16:40:03.0Z","modifiedDays":16550.0,"path":"DSC02045.jpg","imageCaption":"<h5>DSC02045<\/h5><div class=\"comment\">                               <\/div>","fileSize":7879495,"epochDate":1.429955369E12,"name":"DSC02045.jpg","comment":"                               ","category":"image","camera":{"aperture":3.5,"exposureTime":"1\/640s","originalDate":"2015-04-25T12:49:29.0Z","cameraModel":"DSC-HX50","resolution":"5184 x 3888","cameraMake":"SONY","isoEquivalent":80,"flash":"Flash did not fire, auto","focalLength":"4mm"}},{"image":{"path":"slides\/DSC02046.jpg","width":1024,"height":768},"thumb":{"path":"thumbs\/DSC02046.jpg","width":640,"height":480},"thumbCaption":"<span class=\"nr\">5<\/span>  <small>                               <\/small>","photodata":"<p><b>Original Date<\/b> <i>4\/25\/15 12:49 PM<\/i><\/p><p><b>Camera<\/b> <i>DSC-HX50<\/i><\/p><p><b>Focal Length<\/b> <i>4.3 mm<\/i><\/p><p><b>Metering Mode<\/b> <i>Multi-segment<\/i><\/p><p><b>ISO Equivalent<\/b> <i>80<\/i><\/p><p><b>Exposure Time<\/b> <i>1\/500s<\/i><\/p><p><b>Aperture<\/b> <i>3.5<\/i><\/p><p><b>Exposure bias<\/b> <i>0 EV<\/i><\/p><p><b>Exposure Program<\/b> <i>Landscape mode<\/i><\/p><p><b>White balance<\/b> <i>Auto white balance<\/i><\/p><p><b>Flash<\/b> <i>Flash did not fire, auto<\/i><\/p><p><b>Resolution<\/b> <i>5184 x 3888<\/i><\/p>","fileDate":"2015-04-25T16:40:04.0Z","modifiedDays":16550.0,"path":"DSC02046.jpg","imageCaption":"<h5>DSC02046<\/h5><div class=\"comment\">                               <\/div>","fileSize":7189244,"epochDate":1.429955377E12,"name":"DSC02046.jpg","comment":"                               ","category":"image","camera":{"aperture":3.5,"exposureTime":"1\/500s","originalDate":"2015-04-25T12:49:37.0Z","cameraModel":"DSC-HX50","resolution":"5184 x 3888","cameraMake":"SONY","isoEquivalent":80,"flash":"Flash did not fire, auto","focalLength":"4mm"}}],"name":"Чозения толокнянколистная (Chosenia arbutifolia)","epochDateRange":"1429955333000,1429955377000","fileDate":"2017-06-17T20:20:24.217Z","modifiedDays":16550.0}