{"path":"%D0%9A%D0%BE%D0%BB%D0%BE%D1%81%D0%BD%D1%8F%D0%BA%20%D0%BF%D0%B5%D1%81%D1%87%D0%B0%D0%BD%D1%8B%D0%B9%20%28Leymus%20arenarius%29","deepCounters":{"total":7,"images":7,"files":7},"counters":{"total":7,"images":7,"files":7},"thumb":{"path":"thumbs\/DSC00027.JPG","width":640,"height":480},"thumbCaption":"<h3>Колосняк песчаный (Leymus arenarius)<\/h3>","album":{"description":"Plantarium.INFO. Plant anatomy, Hybrids, Pests and Diseases, Carnivorous, Myco-Heterotrophic, Parasitic, Albinos, Fungi, Succulents, Cactuses, Aquatic, Nut-fruited, Tuberous, Ferns, Mosses, Bulbs, Mutants, Witches' brooms, Fairy rings, Prolific petals, Bad luck, Good luck, Colors, Burls, Mycelium, Molds, Journeys.\n<br\/><br\/>\nVisit also Main site of plants and herbs: <a href=\"http:\/\/herbarium.info\">Herbarium.INFO<\/a><br\/>","title":"Plantarium.INFO Herbs Appendix"},"objects":[{"image":{"path":"slides\/DSC00027.JPG","width":768,"height":1024},"thumb":{"path":"thumbs\/DSC00027.JPG","width":640,"height":480},"thumbCaption":"<span class=\"nr\">1<\/span>  <small>                               <\/small>","photodata":"<p><b>Original Date<\/b> <i>7\/29\/17 1:04 PM<\/i><\/p><p><b>Camera<\/b> <i>DSC-HX90<\/i><\/p><p><b>Focal Length (35mm)<\/b> <i>24mm<\/i><\/p><p><b>Metering Mode<\/b> <i>Multi-segment<\/i><\/p><p><b>ISO Equivalent<\/b> <i>80<\/i><\/p><p><b>Exposure Time<\/b> <i>1\/250s<\/i><\/p><p><b>Aperture<\/b> <i>4<\/i><\/p><p><b>Exposure bias<\/b> <i>0 EV<\/i><\/p><p><b>Exposure Program<\/b> <i>Manual control<\/i><\/p><p><b>White balance<\/b> <i>Manual white balance<\/i><\/p><p><b>Flash<\/b> <i>Flash did not fire, auto<\/i><\/p><p><b>Resolution<\/b> <i>4896 x 3672<\/i><\/p>","fileDate":"2017-07-29T13:04:20.0Z","modifiedDays":17376.0,"path":"DSC00027.JPG","imageCaption":"<h5>DSC00027<\/h5><div class=\"comment\">                               <\/div>","fileSize":8799231,"epochDate":1.50132266E12,"name":"DSC00027.JPG","comment":"                               ","category":"image","camera":{"aperture":4.0,"exposureTime":"1\/250s","originalDate":"2017-07-29T13:04:20.0Z","cameraModel":"DSC-HX90","focalLength35mm":"24mm","resolution":"4896 x 3672","cameraMake":"SONY","isoEquivalent":80,"flash":"Flash did not fire, auto","focalLength":"4mm"}},{"image":{"path":"slides\/DSC00028.JPG","width":768,"height":1024},"thumb":{"path":"thumbs\/DSC00028.JPG","width":640,"height":480},"thumbCaption":"<span class=\"nr\">2<\/span>  <small>                               <\/small>","photodata":"<p><b>Original Date<\/b> <i>7\/29\/17 1:04 PM<\/i><\/p><p><b>Camera<\/b> <i>DSC-HX90<\/i><\/p><p><b>Focal Length (35mm)<\/b> <i>24mm<\/i><\/p><p><b>Metering Mode<\/b> <i>Multi-segment<\/i><\/p><p><b>ISO Equivalent<\/b> <i>80<\/i><\/p><p><b>Exposure Time<\/b> <i>1\/320s<\/i><\/p><p><b>Aperture<\/b> <i>4<\/i><\/p><p><b>Exposure bias<\/b> <i>0 EV<\/i><\/p><p><b>Exposure Program<\/b> <i>Manual control<\/i><\/p><p><b>White balance<\/b> <i>Manual white balance<\/i><\/p><p><b>Flash<\/b> <i>Flash did not fire, auto<\/i><\/p><p><b>Resolution<\/b> <i>4896 x 3672<\/i><\/p>","fileDate":"2017-07-29T13:04:30.0Z","modifiedDays":17376.0,"path":"DSC00028.JPG","imageCaption":"<h5>DSC00028<\/h5><div class=\"comment\">                               <\/div>","fileSize":5343421,"epochDate":1.501322671E12,"name":"DSC00028.JPG","comment":"                               ","category":"image","camera":{"aperture":4.0,"exposureTime":"1\/320s","originalDate":"2017-07-29T13:04:31.0Z","cameraModel":"DSC-HX90","focalLength35mm":"24mm","resolution":"4896 x 3672","cameraMake":"SONY","isoEquivalent":80,"flash":"Flash did not fire, auto","focalLength":"4mm"}},{"image":{"path":"slides\/DSC00029.JPG","width":768,"height":1024},"thumb":{"path":"thumbs\/DSC00029.JPG","width":640,"height":480},"thumbCaption":"<span class=\"nr\">3<\/span>  <small>                               <\/small>","photodata":"<p><b>Original Date<\/b> <i>7\/29\/17 1:04 PM<\/i><\/p><p><b>Camera<\/b> <i>DSC-HX90<\/i><\/p><p><b>Focal Length (35mm)<\/b> <i>24mm<\/i><\/p><p><b>Metering Mode<\/b> <i>Multi-segment<\/i><\/p><p><b>ISO Equivalent<\/b> <i>80<\/i><\/p><p><b>Exposure Time<\/b> <i>1\/320s<\/i><\/p><p><b>Aperture<\/b> <i>4<\/i><\/p><p><b>Exposure bias<\/b> <i>0 EV<\/i><\/p><p><b>Exposure Program<\/b> <i>Manual control<\/i><\/p><p><b>White balance<\/b> <i>Manual white balance<\/i><\/p><p><b>Flash<\/b> <i>Flash did not fire, auto<\/i><\/p><p><b>Resolution<\/b> <i>4896 x 3672<\/i><\/p>","fileDate":"2017-07-29T13:04:36.0Z","modifiedDays":17376.0,"path":"DSC00029.JPG","imageCaption":"<h5>DSC00029<\/h5><div class=\"comment\">                               <\/div>","fileSize":4528477,"epochDate":1.501322677E12,"name":"DSC00029.JPG","comment":"                               ","category":"image","camera":{"aperture":4.0,"exposureTime":"1\/320s","originalDate":"2017-07-29T13:04:37.0Z","cameraModel":"DSC-HX90","focalLength35mm":"24mm","resolution":"4896 x 3672","cameraMake":"SONY","isoEquivalent":80,"flash":"Flash did not fire, auto","focalLength":"4mm"}},{"image":{"path":"slides\/DSC00030.JPG","width":1024,"height":768},"thumb":{"path":"thumbs\/DSC00030.JPG","width":640,"height":480},"thumbCaption":"<span class=\"nr\">4<\/span>  <small>                               <\/small>","photodata":"<p><b>Original Date<\/b> <i>7\/29\/17 1:05 PM<\/i><\/p><p><b>Camera<\/b> <i>DSC-HX90<\/i><\/p><p><b>Focal Length (35mm)<\/b> <i>24mm<\/i><\/p><p><b>Metering Mode<\/b> <i>Multi-segment<\/i><\/p><p><b>ISO Equivalent<\/b> <i>80<\/i><\/p><p><b>Exposure Time<\/b> <i>1\/250s<\/i><\/p><p><b>Aperture<\/b> <i>4<\/i><\/p><p><b>Exposure bias<\/b> <i>0 EV<\/i><\/p><p><b>Exposure Program<\/b> <i>Manual control<\/i><\/p><p><b>White balance<\/b> <i>Manual white balance<\/i><\/p><p><b>Flash<\/b> <i>Flash did not fire, auto<\/i><\/p><p><b>Resolution<\/b> <i>4896 x 3672<\/i><\/p>","fileDate":"2017-07-29T13:05:02.0Z","modifiedDays":17376.0,"path":"DSC00030.JPG","imageCaption":"<h5>DSC00030<\/h5><div class=\"comment\">                               <\/div>","fileSize":9342394,"epochDate":1.501322702E12,"name":"DSC00030.JPG","comment":"                               ","category":"image","camera":{"aperture":4.0,"exposureTime":"1\/250s","originalDate":"2017-07-29T13:05:02.0Z","cameraModel":"DSC-HX90","focalLength35mm":"24mm","resolution":"4896 x 3672","cameraMake":"SONY","isoEquivalent":80,"flash":"Flash did not fire, auto","focalLength":"4mm"}},{"image":{"path":"slides\/DSC00031.JPG","width":768,"height":1024},"thumb":{"path":"thumbs\/DSC00031.JPG","width":640,"height":480},"thumbCaption":"<span class=\"nr\">5<\/span>  <small>                               <\/small>","photodata":"<p><b>Original Date<\/b> <i>7\/29\/17 1:05 PM<\/i><\/p><p><b>Camera<\/b> <i>DSC-HX90<\/i><\/p><p><b>Focal Length (35mm)<\/b> <i>24mm<\/i><\/p><p><b>Metering Mode<\/b> <i>Multi-segment<\/i><\/p><p><b>ISO Equivalent<\/b> <i>80<\/i><\/p><p><b>Exposure Time<\/b> <i>1\/200s<\/i><\/p><p><b>Aperture<\/b> <i>4<\/i><\/p><p><b>Exposure bias<\/b> <i>0 EV<\/i><\/p><p><b>Exposure Program<\/b> <i>Manual control<\/i><\/p><p><b>White balance<\/b> <i>Manual white balance<\/i><\/p><p><b>Flash<\/b> <i>Flash did not fire, auto<\/i><\/p><p><b>Resolution<\/b> <i>4896 x 3672<\/i><\/p>","fileDate":"2017-07-29T13:05:46.0Z","modifiedDays":17376.0,"path":"DSC00031.JPG","imageCaption":"<h5>DSC00031<\/h5><div class=\"comment\">                               <\/div>","fileSize":7354888,"epochDate":1.501322747E12,"name":"DSC00031.JPG","comment":"                               ","category":"image","camera":{"aperture":4.0,"exposureTime":"1\/200s","originalDate":"2017-07-29T13:05:47.0Z","cameraModel":"DSC-HX90","focalLength35mm":"24mm","resolution":"4896 x 3672","cameraMake":"SONY","isoEquivalent":80,"flash":"Flash did not fire, auto","focalLength":"4mm"}},{"image":{"path":"slides\/DSC00032.JPG","width":768,"height":1024},"thumb":{"path":"thumbs\/DSC00032.JPG","width":640,"height":480},"thumbCaption":"<span class=\"nr\">6<\/span>  <small>                               <\/small>","photodata":"<p><b>Original Date<\/b> <i>7\/29\/17 1:05 PM<\/i><\/p><p><b>Camera<\/b> <i>DSC-HX90<\/i><\/p><p><b>Focal Length (35mm)<\/b> <i>24mm<\/i><\/p><p><b>Metering Mode<\/b> <i>Multi-segment<\/i><\/p><p><b>ISO Equivalent<\/b> <i>80<\/i><\/p><p><b>Exposure Time<\/b> <i>1\/200s<\/i><\/p><p><b>Aperture<\/b> <i>4<\/i><\/p><p><b>Exposure bias<\/b> <i>0 EV<\/i><\/p><p><b>Exposure Program<\/b> <i>Manual control<\/i><\/p><p><b>White balance<\/b> <i>Manual white balance<\/i><\/p><p><b>Flash<\/b> <i>Flash did not fire, auto<\/i><\/p><p><b>Resolution<\/b> <i>4896 x 3672<\/i><\/p>","fileDate":"2017-07-29T13:05:52.0Z","modifiedDays":17376.0,"path":"DSC00032.JPG","imageCaption":"<h5>DSC00032<\/h5><div class=\"comment\">                               <\/div>","fileSize":7761488,"epochDate":1.501322752E12,"name":"DSC00032.JPG","comment":"                               ","category":"image","camera":{"aperture":4.0,"exposureTime":"1\/200s","originalDate":"2017-07-29T13:05:52.0Z","cameraModel":"DSC-HX90","focalLength35mm":"24mm","resolution":"4896 x 3672","cameraMake":"SONY","isoEquivalent":80,"flash":"Flash did not fire, auto","focalLength":"4mm"}},{"image":{"path":"slides\/DSC00033.JPG","width":768,"height":1024},"thumb":{"path":"thumbs\/DSC00033.JPG","width":640,"height":480},"thumbCaption":"<span class=\"nr\">7<\/span>  <small>                               <\/small>","photodata":"<p><b>Original Date<\/b> <i>7\/29\/17 1:06 PM<\/i><\/p><p><b>Camera<\/b> <i>DSC-HX90<\/i><\/p><p><b>Focal Length (35mm)<\/b> <i>24mm<\/i><\/p><p><b>Metering Mode<\/b> <i>Multi-segment<\/i><\/p><p><b>ISO Equivalent<\/b> <i>80<\/i><\/p><p><b>Exposure Time<\/b> <i>1\/200s<\/i><\/p><p><b>Aperture<\/b> <i>4<\/i><\/p><p><b>Exposure bias<\/b> <i>0 EV<\/i><\/p><p><b>Exposure Program<\/b> <i>Manual control<\/i><\/p><p><b>White balance<\/b> <i>Manual white balance<\/i><\/p><p><b>Flash<\/b> <i>Flash did not fire, auto<\/i><\/p><p><b>Resolution<\/b> <i>4896 x 3672<\/i><\/p>","fileDate":"2017-07-29T13:06:00.0Z","modifiedDays":17376.0,"path":"DSC00033.JPG","imageCaption":"<h5>DSC00033<\/h5><div class=\"comment\">                               <\/div>","fileSize":6436095,"epochDate":1.50132276E12,"name":"DSC00033.JPG","comment":"                               ","category":"image","camera":{"aperture":4.0,"exposureTime":"1\/200s","originalDate":"2017-07-29T13:06:00.0Z","cameraModel":"DSC-HX90","focalLength35mm":"24mm","resolution":"4896 x 3672","cameraMake":"SONY","isoEquivalent":80,"flash":"Flash did not fire, auto","focalLength":"4mm"}}],"name":"Колосняк песчаный (Leymus arenarius)","epochDateRange":"1501322660000,1501322760000","fileDate":"2017-10-09T20:55:47.503Z","modifiedDays":17376.0}