{"path":"%D0%90%D1%80%D0%B0%D1%85%D0%B8%D1%81%20%D0%BA%D1%83%D0%BB%D1%8C%D1%82%D1%83%D1%80%D0%BD%D1%8B%D0%B9%2C%20%D0%BF%D0%BE%D0%B4%D0%B7%D0%B5%D0%BC%D0%BD%D1%8B%D0%B9%20%28Arachis%20hypogaea%29","deepCounters":{"total":12,"images":12,"files":12},"counters":{"total":12,"images":12,"files":12},"thumb":{"path":"thumbs\/DSC07736.jpg","width":640,"height":480},"thumbCaption":"<h3>Арахис культурный, подземный (Arachis hypogaea)<\/h3>","album":{"description":"Plantarium.INFO. Plant anatomy, Hybrids, Pests and Diseases, Carnivorous, Myco-Heterotrophic, Parasitic, Albinos, Fungi, Succulents, Cactuses, Aquatic, Nut-fruited, Tuberous, Ferns, Mosses, Bulbs, Mutants, Witches' brooms, Fairy rings, Prolific petals, Bad luck, Good luck, Colors, Burls, Mycelium, Molds, Journeys.\n<br\/><br\/>\nVisit also Main site of plants and herbs: <a href=\"http:\/\/herbarium.info\">Herbarium.INFO<\/a><br\/>","title":"Plantarium.INFO Herbs Appendix"},"objects":[{"image":{"path":"slides\/DSC07736.jpg","width":1024,"height":768},"thumb":{"path":"thumbs\/DSC07736.jpg","width":640,"height":480},"thumbCaption":"<span class=\"nr\">1<\/span>  <small>                               <\/small>","photodata":"<p><b>Original Date<\/b> <i>11\/30\/15 6:45 PM<\/i><\/p><p><b>Camera<\/b> <i>DSC-HX50<\/i><\/p><p><b>Focal Length<\/b> <i>4.3 mm<\/i><\/p><p><b>Metering Mode<\/b> <i>Multi-segment<\/i><\/p><p><b>ISO Equivalent<\/b> <i>200<\/i><\/p><p><b>Exposure Time<\/b> <i>1\/100s<\/i><\/p><p><b>Aperture<\/b> <i>3.5<\/i><\/p><p><b>Exposure bias<\/b> <i>0 EV<\/i><\/p><p><b>Exposure Program<\/b> <i>Manual control<\/i><\/p><p><b>White balance<\/b> <i>Manual white balance<\/i><\/p><p><b>Flash<\/b> <i>Flash did not fire, auto<\/i><\/p><p><b>Resolution<\/b> <i>5184 x 3888<\/i><\/p>","fileDate":"2015-11-30T18:42:14.0Z","modifiedDays":16770.0,"path":"DSC07736.jpg","imageCaption":"<h5>DSC07736<\/h5><div class=\"comment\">                               <\/div>","fileSize":6579948,"epochDate":1.448898304E12,"name":"DSC07736.jpg","comment":"                               ","category":"image","camera":{"aperture":3.5,"exposureTime":"1\/100s","originalDate":"2015-11-30T18:45:04.0Z","cameraModel":"DSC-HX50","resolution":"5184 x 3888","cameraMake":"SONY","isoEquivalent":200,"flash":"Flash did not fire, auto","focalLength":"4mm"}},{"image":{"path":"slides\/DSC07737.jpg","width":1024,"height":768},"thumb":{"path":"thumbs\/DSC07737.jpg","width":640,"height":480},"thumbCaption":"<span class=\"nr\">2<\/span>  <small>                               <\/small>","photodata":"<p><b>Original Date<\/b> <i>11\/30\/15 6:45 PM<\/i><\/p><p><b>Camera<\/b> <i>DSC-HX50<\/i><\/p><p><b>Focal Length<\/b> <i>4.3 mm<\/i><\/p><p><b>Metering Mode<\/b> <i>Multi-segment<\/i><\/p><p><b>ISO Equivalent<\/b> <i>200<\/i><\/p><p><b>Exposure Time<\/b> <i>1\/100s<\/i><\/p><p><b>Aperture<\/b> <i>3.5<\/i><\/p><p><b>Exposure bias<\/b> <i>0 EV<\/i><\/p><p><b>Exposure Program<\/b> <i>Manual control<\/i><\/p><p><b>White balance<\/b> <i>Manual white balance<\/i><\/p><p><b>Flash<\/b> <i>Flash did not fire, auto<\/i><\/p><p><b>Resolution<\/b> <i>5184 x 3888<\/i><\/p>","fileDate":"2015-11-30T18:42:15.0Z","modifiedDays":16770.0,"path":"DSC07737.jpg","imageCaption":"<h5>DSC07737<\/h5><div class=\"comment\">                               <\/div>","fileSize":6630912,"epochDate":1.448898309E12,"name":"DSC07737.jpg","comment":"                               ","category":"image","camera":{"aperture":3.5,"exposureTime":"1\/100s","originalDate":"2015-11-30T18:45:09.0Z","cameraModel":"DSC-HX50","resolution":"5184 x 3888","cameraMake":"SONY","isoEquivalent":200,"flash":"Flash did not fire, auto","focalLength":"4mm"}},{"image":{"path":"slides\/DSC07738.jpg","width":1024,"height":768},"thumb":{"path":"thumbs\/DSC07738.jpg","width":640,"height":480},"thumbCaption":"<span class=\"nr\">3<\/span>  <small>                               <\/small>","photodata":"<p><b>Original Date<\/b> <i>11\/30\/15 6:45 PM<\/i><\/p><p><b>Camera<\/b> <i>DSC-HX50<\/i><\/p><p><b>Focal Length<\/b> <i>4.3 mm<\/i><\/p><p><b>Metering Mode<\/b> <i>Multi-segment<\/i><\/p><p><b>ISO Equivalent<\/b> <i>200<\/i><\/p><p><b>Exposure Time<\/b> <i>1\/80s<\/i><\/p><p><b>Aperture<\/b> <i>4<\/i><\/p><p><b>Exposure bias<\/b> <i>0 EV<\/i><\/p><p><b>Exposure Program<\/b> <i>Manual control<\/i><\/p><p><b>White balance<\/b> <i>Manual white balance<\/i><\/p><p><b>Flash<\/b> <i>Flash did not fire, auto<\/i><\/p><p><b>Resolution<\/b> <i>5184 x 3888<\/i><\/p>","fileDate":"2015-11-30T18:42:16.0Z","modifiedDays":16770.0,"path":"DSC07738.jpg","imageCaption":"<h5>DSC07738<\/h5><div class=\"comment\">                               <\/div>","fileSize":6951306,"epochDate":1.448898325E12,"name":"DSC07738.jpg","comment":"                               ","category":"image","camera":{"aperture":4.0,"exposureTime":"1\/80s","originalDate":"2015-11-30T18:45:25.0Z","cameraModel":"DSC-HX50","resolution":"5184 x 3888","cameraMake":"SONY","isoEquivalent":200,"flash":"Flash did not fire, auto","focalLength":"4mm"}},{"image":{"path":"slides\/DSC07739.jpg","width":1024,"height":768},"thumb":{"path":"thumbs\/DSC07739.jpg","width":640,"height":480},"thumbCaption":"<span class=\"nr\">4<\/span>  <small>                               <\/small>","photodata":"<p><b>Original Date<\/b> <i>11\/30\/15 6:45 PM<\/i><\/p><p><b>Camera<\/b> <i>DSC-HX50<\/i><\/p><p><b>Focal Length<\/b> <i>4.3 mm<\/i><\/p><p><b>Metering Mode<\/b> <i>Multi-segment<\/i><\/p><p><b>ISO Equivalent<\/b> <i>200<\/i><\/p><p><b>Exposure Time<\/b> <i>1\/80s<\/i><\/p><p><b>Aperture<\/b> <i>4<\/i><\/p><p><b>Exposure bias<\/b> <i>0 EV<\/i><\/p><p><b>Exposure Program<\/b> <i>Manual control<\/i><\/p><p><b>White balance<\/b> <i>Manual white balance<\/i><\/p><p><b>Flash<\/b> <i>Flash did not fire, auto<\/i><\/p><p><b>Resolution<\/b> <i>5184 x 3888<\/i><\/p>","fileDate":"2015-11-30T18:42:16.0Z","modifiedDays":16770.0,"path":"DSC07739.jpg","imageCaption":"<h5>DSC07739<\/h5><div class=\"comment\">                               <\/div>","fileSize":6965521,"epochDate":1.448898329E12,"name":"DSC07739.jpg","comment":"                               ","category":"image","camera":{"aperture":4.0,"exposureTime":"1\/80s","originalDate":"2015-11-30T18:45:29.0Z","cameraModel":"DSC-HX50","resolution":"5184 x 3888","cameraMake":"SONY","isoEquivalent":200,"flash":"Flash did not fire, auto","focalLength":"4mm"}},{"image":{"path":"slides\/DSC07740.jpg","width":1024,"height":768},"thumb":{"path":"thumbs\/DSC07740.jpg","width":640,"height":480},"thumbCaption":"<span class=\"nr\">5<\/span>  <small>                               <\/small>","photodata":"<p><b>Original Date<\/b> <i>11\/30\/15 6:45 PM<\/i><\/p><p><b>Camera<\/b> <i>DSC-HX50<\/i><\/p><p><b>Focal Length<\/b> <i>6.3 mm<\/i><\/p><p><b>Metering Mode<\/b> <i>Multi-segment<\/i><\/p><p><b>ISO Equivalent<\/b> <i>200<\/i><\/p><p><b>Exposure Time<\/b> <i>1\/60s<\/i><\/p><p><b>Aperture<\/b> <i>4<\/i><\/p><p><b>Exposure bias<\/b> <i>0 EV<\/i><\/p><p><b>Exposure Program<\/b> <i>Manual control<\/i><\/p><p><b>White balance<\/b> <i>Manual white balance<\/i><\/p><p><b>Flash<\/b> <i>Flash did not fire, auto<\/i><\/p><p><b>Resolution<\/b> <i>5184 x 3888<\/i><\/p>","fileDate":"2015-11-30T18:42:17.0Z","modifiedDays":16770.0,"path":"DSC07740.jpg","imageCaption":"<h5>DSC07740<\/h5><div class=\"comment\">                               <\/div>","fileSize":7306861,"epochDate":1.448898357E12,"name":"DSC07740.jpg","comment":"                               ","category":"image","camera":{"aperture":4.0,"exposureTime":"1\/60s","originalDate":"2015-11-30T18:45:57.0Z","cameraModel":"DSC-HX50","resolution":"5184 x 3888","cameraMake":"SONY","isoEquivalent":200,"flash":"Flash did not fire, auto","focalLength":"6mm"}},{"image":{"path":"slides\/DSC07741.jpg","width":1024,"height":768},"thumb":{"path":"thumbs\/DSC07741.jpg","width":640,"height":480},"thumbCaption":"<span class=\"nr\">6<\/span>  <small>                               <\/small>","photodata":"<p><b>Original Date<\/b> <i>11\/30\/15 6:46 PM<\/i><\/p><p><b>Camera<\/b> <i>DSC-HX50<\/i><\/p><p><b>Focal Length<\/b> <i>6.3 mm<\/i><\/p><p><b>Metering Mode<\/b> <i>Multi-segment<\/i><\/p><p><b>ISO Equivalent<\/b> <i>200<\/i><\/p><p><b>Exposure Time<\/b> <i>1\/60s<\/i><\/p><p><b>Aperture<\/b> <i>4<\/i><\/p><p><b>Exposure bias<\/b> <i>0 EV<\/i><\/p><p><b>Exposure Program<\/b> <i>Manual control<\/i><\/p><p><b>White balance<\/b> <i>Manual white balance<\/i><\/p><p><b>Flash<\/b> <i>Flash did not fire, auto<\/i><\/p><p><b>Resolution<\/b> <i>5184 x 3888<\/i><\/p>","fileDate":"2015-11-30T18:42:18.0Z","modifiedDays":16770.0,"path":"DSC07741.jpg","imageCaption":"<h5>DSC07741<\/h5><div class=\"comment\">                               <\/div>","fileSize":7477100,"epochDate":1.44889836E12,"name":"DSC07741.jpg","comment":"                               ","category":"image","camera":{"aperture":4.0,"exposureTime":"1\/60s","originalDate":"2015-11-30T18:46:00.0Z","cameraModel":"DSC-HX50","resolution":"5184 x 3888","cameraMake":"SONY","isoEquivalent":200,"flash":"Flash did not fire, auto","focalLength":"6mm"}},{"image":{"path":"slides\/DSC07742.jpg","width":1024,"height":768},"thumb":{"path":"thumbs\/DSC07742.jpg","width":640,"height":480},"thumbCaption":"<span class=\"nr\">7<\/span>  <small>                               <\/small>","photodata":"<p><b>Original Date<\/b> <i>11\/30\/15 6:46 PM<\/i><\/p><p><b>Camera<\/b> <i>DSC-HX50<\/i><\/p><p><b>Focal Length<\/b> <i>6.3 mm<\/i><\/p><p><b>Metering Mode<\/b> <i>Multi-segment<\/i><\/p><p><b>ISO Equivalent<\/b> <i>200<\/i><\/p><p><b>Exposure Time<\/b> <i>1\/60s<\/i><\/p><p><b>Aperture<\/b> <i>4<\/i><\/p><p><b>Exposure bias<\/b> <i>0 EV<\/i><\/p><p><b>Exposure Program<\/b> <i>Manual control<\/i><\/p><p><b>White balance<\/b> <i>Manual white balance<\/i><\/p><p><b>Flash<\/b> <i>Flash did not fire, auto<\/i><\/p><p><b>Resolution<\/b> <i>5184 x 3888<\/i><\/p>","fileDate":"2015-11-30T18:42:19.0Z","modifiedDays":16770.0,"path":"DSC07742.jpg","imageCaption":"<h5>DSC07742<\/h5><div class=\"comment\">                               <\/div>","fileSize":7528539,"epochDate":1.448898364E12,"name":"DSC07742.jpg","comment":"                               ","category":"image","camera":{"aperture":4.0,"exposureTime":"1\/60s","originalDate":"2015-11-30T18:46:04.0Z","cameraModel":"DSC-HX50","resolution":"5184 x 3888","cameraMake":"SONY","isoEquivalent":200,"flash":"Flash did not fire, auto","focalLength":"6mm"}},{"image":{"path":"slides\/DSC07743.jpg","width":1024,"height":768},"thumb":{"path":"thumbs\/DSC07743.jpg","width":640,"height":480},"thumbCaption":"<span class=\"nr\">8<\/span>  <small>                               <\/small>","photodata":"<p><b>Original Date<\/b> <i>11\/30\/15 6:46 PM<\/i><\/p><p><b>Camera<\/b> <i>DSC-HX50<\/i><\/p><p><b>Focal Length<\/b> <i>6.3 mm<\/i><\/p><p><b>Metering Mode<\/b> <i>Multi-segment<\/i><\/p><p><b>ISO Equivalent<\/b> <i>200<\/i><\/p><p><b>Exposure Time<\/b> <i>1\/60s<\/i><\/p><p><b>Aperture<\/b> <i>4<\/i><\/p><p><b>Exposure bias<\/b> <i>0 EV<\/i><\/p><p><b>Exposure Program<\/b> <i>Manual control<\/i><\/p><p><b>White balance<\/b> <i>Manual white balance<\/i><\/p><p><b>Flash<\/b> <i>Flash did not fire, auto<\/i><\/p><p><b>Resolution<\/b> <i>5184 x 3888<\/i><\/p>","fileDate":"2015-11-30T18:42:20.0Z","modifiedDays":16770.0,"path":"DSC07743.jpg","imageCaption":"<h5>DSC07743<\/h5><div class=\"comment\">                               <\/div>","fileSize":6018741,"epochDate":1.448898393E12,"name":"DSC07743.jpg","comment":"                               ","category":"image","camera":{"aperture":4.0,"exposureTime":"1\/60s","originalDate":"2015-11-30T18:46:33.0Z","cameraModel":"DSC-HX50","resolution":"5184 x 3888","cameraMake":"SONY","isoEquivalent":200,"flash":"Flash did not fire, auto","focalLength":"6mm"}},{"image":{"path":"slides\/DSC07744.jpg","width":1024,"height":768},"thumb":{"path":"thumbs\/DSC07744.jpg","width":640,"height":480},"thumbCaption":"<span class=\"nr\">9<\/span>  <small>                               <\/small>","photodata":"<p><b>Original Date<\/b> <i>11\/30\/15 6:46 PM<\/i><\/p><p><b>Camera<\/b> <i>DSC-HX50<\/i><\/p><p><b>Focal Length<\/b> <i>6.3 mm<\/i><\/p><p><b>Metering Mode<\/b> <i>Multi-segment<\/i><\/p><p><b>ISO Equivalent<\/b> <i>200<\/i><\/p><p><b>Exposure Time<\/b> <i>1\/60s<\/i><\/p><p><b>Aperture<\/b> <i>4<\/i><\/p><p><b>Exposure bias<\/b> <i>0 EV<\/i><\/p><p><b>Exposure Program<\/b> <i>Manual control<\/i><\/p><p><b>White balance<\/b> <i>Manual white balance<\/i><\/p><p><b>Flash<\/b> <i>Flash did not fire, auto<\/i><\/p><p><b>Resolution<\/b> <i>5184 x 3888<\/i><\/p>","fileDate":"2015-11-30T18:42:21.0Z","modifiedDays":16770.0,"path":"DSC07744.jpg","imageCaption":"<h5>DSC07744<\/h5><div class=\"comment\">                               <\/div>","fileSize":5916204,"epochDate":1.448898397E12,"name":"DSC07744.jpg","comment":"                               ","category":"image","camera":{"aperture":4.0,"exposureTime":"1\/60s","originalDate":"2015-11-30T18:46:37.0Z","cameraModel":"DSC-HX50","resolution":"5184 x 3888","cameraMake":"SONY","isoEquivalent":200,"flash":"Flash did not fire, auto","focalLength":"6mm"}},{"image":{"path":"slides\/DSC07745.jpg","width":1024,"height":768},"thumb":{"path":"thumbs\/DSC07745.jpg","width":640,"height":480},"thumbCaption":"<span class=\"nr\">10<\/span>  <small>                               <\/small>","photodata":"<p><b>Original Date<\/b> <i>11\/30\/15 6:46 PM<\/i><\/p><p><b>Camera<\/b> <i>DSC-HX50<\/i><\/p><p><b>Focal Length<\/b> <i>6.3 mm<\/i><\/p><p><b>Metering Mode<\/b> <i>Multi-segment<\/i><\/p><p><b>ISO Equivalent<\/b> <i>200<\/i><\/p><p><b>Exposure Time<\/b> <i>1\/60s<\/i><\/p><p><b>Aperture<\/b> <i>4<\/i><\/p><p><b>Exposure bias<\/b> <i>0 EV<\/i><\/p><p><b>Exposure Program<\/b> <i>Manual control<\/i><\/p><p><b>White balance<\/b> <i>Manual white balance<\/i><\/p><p><b>Flash<\/b> <i>Flash did not fire, auto<\/i><\/p><p><b>Resolution<\/b> <i>5184 x 3888<\/i><\/p>","fileDate":"2015-11-30T18:42:21.0Z","modifiedDays":16770.0,"path":"DSC07745.jpg","imageCaption":"<h5>DSC07745<\/h5><div class=\"comment\">                               <\/div>","fileSize":5866729,"epochDate":1.448898401E12,"name":"DSC07745.jpg","comment":"                               ","category":"image","camera":{"aperture":4.0,"exposureTime":"1\/60s","originalDate":"2015-11-30T18:46:41.0Z","cameraModel":"DSC-HX50","resolution":"5184 x 3888","cameraMake":"SONY","isoEquivalent":200,"flash":"Flash did not fire, auto","focalLength":"6mm"}},{"image":{"path":"slides\/DSC07746.jpg","width":1024,"height":768},"thumb":{"path":"thumbs\/DSC07746.jpg","width":640,"height":480},"thumbCaption":"<span class=\"nr\">11<\/span>  <small>                               <\/small>","photodata":"<p><b>Original Date<\/b> <i>11\/30\/15 6:49 PM<\/i><\/p><p><b>Camera<\/b> <i>DSC-HX50<\/i><\/p><p><b>Focal Length<\/b> <i>5.5 mm<\/i><\/p><p><b>Metering Mode<\/b> <i>Multi-segment<\/i><\/p><p><b>ISO Equivalent<\/b> <i>200<\/i><\/p><p><b>Exposure Time<\/b> <i>1\/60s<\/i><\/p><p><b>Aperture<\/b> <i>4<\/i><\/p><p><b>Exposure bias<\/b> <i>0 EV<\/i><\/p><p><b>Exposure Program<\/b> <i>Manual control<\/i><\/p><p><b>White balance<\/b> <i>Manual white balance<\/i><\/p><p><b>Flash<\/b> <i>Flash did not fire, auto<\/i><\/p><p><b>Resolution<\/b> <i>5184 x 3888<\/i><\/p>","fileDate":"2015-11-30T18:42:22.0Z","modifiedDays":16770.0,"path":"DSC07746.jpg","imageCaption":"<h5>DSC07746<\/h5><div class=\"comment\">                               <\/div>","fileSize":4934233,"epochDate":1.448898589E12,"name":"DSC07746.jpg","comment":"                               ","category":"image","camera":{"aperture":4.0,"exposureTime":"1\/60s","originalDate":"2015-11-30T18:49:49.0Z","cameraModel":"DSC-HX50","resolution":"5184 x 3888","cameraMake":"SONY","isoEquivalent":200,"flash":"Flash did not fire, auto","focalLength":"6mm"}},{"image":{"path":"slides\/DSC07747.jpg","width":1024,"height":768},"thumb":{"path":"thumbs\/DSC07747.jpg","width":640,"height":480},"thumbCaption":"<span class=\"nr\">12<\/span>  <small>                               <\/small>","photodata":"<p><b>Original Date<\/b> <i>11\/30\/15 6:49 PM<\/i><\/p><p><b>Camera<\/b> <i>DSC-HX50<\/i><\/p><p><b>Focal Length<\/b> <i>5.5 mm<\/i><\/p><p><b>Metering Mode<\/b> <i>Multi-segment<\/i><\/p><p><b>ISO Equivalent<\/b> <i>200<\/i><\/p><p><b>Exposure Time<\/b> <i>1\/60s<\/i><\/p><p><b>Aperture<\/b> <i>4<\/i><\/p><p><b>Exposure bias<\/b> <i>0 EV<\/i><\/p><p><b>Exposure Program<\/b> <i>Manual control<\/i><\/p><p><b>White balance<\/b> <i>Manual white balance<\/i><\/p><p><b>Flash<\/b> <i>Flash did not fire, auto<\/i><\/p><p><b>Resolution<\/b> <i>5184 x 3888<\/i><\/p>","fileDate":"2015-11-30T18:42:23.0Z","modifiedDays":16770.0,"path":"DSC07747.jpg","imageCaption":"<h5>DSC07747<\/h5><div class=\"comment\">                               <\/div>","fileSize":4947430,"epochDate":1.448898595E12,"name":"DSC07747.jpg","comment":"                               ","category":"image","camera":{"aperture":4.0,"exposureTime":"1\/60s","originalDate":"2015-11-30T18:49:55.0Z","cameraModel":"DSC-HX50","resolution":"5184 x 3888","cameraMake":"SONY","isoEquivalent":200,"flash":"Flash did not fire, auto","focalLength":"6mm"}}],"name":"Арахис культурный, подземный (Arachis hypogaea)","epochDateRange":"1448898304000,1448898595000","fileDate":"2017-06-17T20:20:49.58Z","modifiedDays":16770.0}